{
    "Carriers": [
        {
            "CarrierId": 870,
            "Name": "jetBlue"
        },
        {
            "CarrierId": 1467,
            "Name": "Spirit Airlines"
        },
        {
            "CarrierId": 1793,
            "Name": "United"
        },
        {
            "CarrierId": 1902,
            "Name": "Southwest Airlines"
        }
    ],
    "Currencies": [
        {
            "Code": "USD",
            "DecimalDigits": 2,
            "DecimalSeparator": ".",
            "RoundingCoefficient": 0,
            "SpaceBetweenAmountAndSymbol": false,
            "Symbol": "$",
            "SymbolOnLeft": true,
            "ThousandsSeparator": ","
        }
    ],
    "Places": [
        {
            "CityId": "BOSA",
            "CityName": "Boston",
            "CountryName": "United States",
            "IataCode": "BOS",
            "Name": "Boston Logan International",
            "PlaceId": 42995,
            "SkyscannerCode": "BOS",
            "Type": "Station"
        },
        {
            "CityId": "WASA",
            "CityName": "Washington",
            "CountryName": "United States",
            "IataCode": "BWI",
            "Name": "Baltimore Washington International",
            "PlaceId": 43369,
            "SkyscannerCode": "BWI",
            "Type": "Station"
        }
    ],
    "Quotes": [
        {
            "Direct": true,
            "InboundLeg": {
                "CarrierIds": [
                    870
                ],
                "DepartureDate": "2017-07-23T00:00:00",
                "DestinationId": 42995,
                "OriginId": 43369
            },
            "MinPrice": 163.0,
            "OutboundLeg": {
                "CarrierIds": [
                    870
                ],
                "DepartureDate": "2017-07-21T00:00:00",
                "DestinationId": 43369,
                "OriginId": 42995
            },
            "QuoteDateTime": "2017-04-22T13:41:00",
            "QuoteId": 1
        }
    ]
}