{
    "Carriers": [
        {
            "CarrierId": 819,
            "Name": "Aegean Airlines"
        },
        {
            "CarrierId": 1427,
            "Name": "EgyptAir"
        }
    ],
    "Currencies": [
        {
            "Code": "USD",
            "DecimalDigits": 2,
            "DecimalSeparator": ".",
            "RoundingCoefficient": 0,
            "SpaceBetweenAmountAndSymbol": false,
            "Symbol": "$",
            "SymbolOnLeft": true,
            "ThousandsSeparator": ","
        }
    ],
    "Places": [
        {
            "Name": "United Arab Emirates",
            "PlaceId": 837,
            "SkyscannerCode": "AE",
            "Type": "Country"
        },
        {
            "Name": "Austria",
            "PlaceId": 852,
            "SkyscannerCode": "AT",
            "Type": "Country"
        },
        {
            "Name": "Belgium",
            "PlaceId": 885,
            "SkyscannerCode": "BE",
            "Type": "Country"
        },
        {
            "Name": "Bahrain",
            "PlaceId": 888,
            "SkyscannerCode": "BH",
            "Type": "Country"
        },
        {
            "Name": "Canada",
            "PlaceId": 929,
            "SkyscannerCode": "CA",
            "Type": "Country"
        },
        {
            "Name": "Central African Republic",
            "PlaceId": 934,
            "SkyscannerCode": "CF",
            "Type": "Country"
        },
        {
            "Name": "Switzerland",
            "PlaceId": 936,
            "SkyscannerCode": "CH",
            "Type": "Country"
        },
        {
            "Name": "Ivory Coast",
            "PlaceId": 937,
            "SkyscannerCode": "CI",
            "Type": "Country"
        },
        {
            "Name": "China",
            "PlaceId": 942,
            "SkyscannerCode": "CN",
            "Type": "Country"
        },
        {
            "Name": "Cyprus",
            "PlaceId": 953,
            "SkyscannerCode": "CY",
            "Type": "Country"
        },
        {
            "Name": "Germany",
            "PlaceId": 981,
            "SkyscannerCode": "DE",
            "Type": "Country"
        },
        {
            "Name": "Denmark",
            "PlaceId": 987,
            "SkyscannerCode": "DK",
            "Type": "Country"
        },
        {
            "Name": "Algeria",
            "PlaceId": 1002,
            "SkyscannerCode": "DZ",
            "Type": "Country"
        },
        {
            "Name": "Egypt",
            "PlaceId": 1031,
            "SkyscannerCode": "EG",
            "Type": "Country"
        },
        {
            "Name": "Eritrea",
            "PlaceId": 1042,
            "SkyscannerCode": "ER",
            "Type": "Country"
        },
        {
            "Name": "Spain",
            "PlaceId": 1043,
            "SkyscannerCode": "ES",
            "Type": "Country"
        },
        {
            "Name": "Ethiopia",
            "PlaceId": 1044,
            "SkyscannerCode": "ET",
            "Type": "Country"
        },
        {
            "Name": "France",
            "PlaceId": 1090,
            "SkyscannerCode": "FR",
            "Type": "Country"
        },
        {
            "Name": "Ghana",
            "PlaceId": 1128,
            "SkyscannerCode": "GH",
            "Type": "Country"
        },
        {
            "Name": "Greece",
            "PlaceId": 1138,
            "SkyscannerCode": "GR",
            "Type": "Country"
        },
        {
            "Name": "Croatia",
            "PlaceId": 1186,
            "SkyscannerCode": "HR",
            "Type": "Country"
        },
        {
            "Name": "Hungary",
            "PlaceId": 1189,
            "SkyscannerCode": "HU",
            "Type": "Country"
        },
        {
            "Name": "Indonesia",
            "PlaceId": 1220,
            "SkyscannerCode": "ID",
            "Type": "Country"
        },
        {
            "Name": "Israel",
            "PlaceId": 1228,
            "SkyscannerCode": "IL",
            "Type": "Country"
        },
        {
            "Name": "India",
            "PlaceId": 1230,
            "SkyscannerCode": "IN",
            "Type": "Country"
        },
        {
            "Name": "Iraq",
            "PlaceId": 1233,
            "SkyscannerCode": "IQ",
            "Type": "Country"
        },
        {
            "Name": "Italy",
            "PlaceId": 1236,
            "SkyscannerCode": "IT",
            "Type": "Country"
        },
        {
            "Name": "Jordan",
            "PlaceId": 1279,
            "SkyscannerCode": "JO",
            "Type": "Country"
        },
        {
            "Name": "Kenya",
            "PlaceId": 1317,
            "SkyscannerCode": "KE",
            "Type": "Country"
        },
        {
            "Name": "Kuwait",
            "PlaceId": 1335,
            "SkyscannerCode": "KW",
            "Type": "Country"
        },
        {
            "Name": "Lebanon",
            "PlaceId": 1362,
            "SkyscannerCode": "LB",
            "Type": "Country"
        },
        {
            "Name": "Morocco",
            "PlaceId": 1409,
            "SkyscannerCode": "MA",
            "Type": "Country"
        },
        {
            "Name": "Malaysia",
            "PlaceId": 1433,
            "SkyscannerCode": "MY",
            "Type": "Country"
        },
        {
            "Name": "Nigeria",
            "PlaceId": 1463,
            "SkyscannerCode": "NG",
            "Type": "Country"
        },
        {
            "Name": "Netherlands",
            "PlaceId": 1468,
            "SkyscannerCode": "NL",
            "Type": "Country"
        },
        {
            "Name": "Oman",
            "PlaceId": 1517,
            "SkyscannerCode": "OM",
            "Type": "Country"
        },
        {
            "Name": "Qatar",
            "PlaceId": 1601,
            "SkyscannerCode": "QA",
            "Type": "Country"
        },
        {
            "Name": "Saudi Arabia",
            "PlaceId": 1697,
            "SkyscannerCode": "SA",
            "Type": "Country"
        },
        {
            "Name": "Sudan",
            "PlaceId": 1700,
            "SkyscannerCode": "SD",
            "Type": "Country"
        },
        {
            "Name": "South Sudan",
            "PlaceId": 1715,
            "SkyscannerCode": "SS",
            "Type": "Country"
        },
        {
            "Name": "Chad",
            "PlaceId": 1748,
            "SkyscannerCode": "TD",
            "Type": "Country"
        },
        {
            "Name": "Thailand",
            "PlaceId": 1752,
            "SkyscannerCode": "TH",
            "Type": "Country"
        },
        {
            "Name": "Tunisia",
            "PlaceId": 1758,
            "SkyscannerCode": "TN",
            "Type": "Country"
        },
        {
            "Name": "Turkey",
            "PlaceId": 1762,
            "SkyscannerCode": "TR",
            "Type": "Country"
        },
        {
            "Name": "Tanzania",
            "PlaceId": 1770,
            "SkyscannerCode": "TZ",
            "Type": "Country"
        },
        {
            "Name": "Uganda",
            "PlaceId": 1799,
            "SkyscannerCode": "UG",
            "Type": "Country"
        },
        {
            "Name": "United Kingdom",
            "PlaceId": 1803,
            "SkyscannerCode": "UK",
            "Type": "Country"
        },
        {
            "Name": "United States",
            "PlaceId": 1811,
            "SkyscannerCode": "US",
            "Type": "Country"
        },
        {
            "Name": "South Africa",
            "PlaceId": 2033,
            "SkyscannerCode": "ZA",
            "Type": "Country"
        },
        {
            "Name": "Zambia",
            "PlaceId": 2045,
            "SkyscannerCode": "ZM",
            "Type": "Country"
        },
        {
            "CityId": "AMMA",
            "CityName": "Amman",
            "CountryName": "Jordan",
            "IataCode": "AMM",
            "Name": "Amman Queen Alia",
            "PlaceId": 40589,
            "SkyscannerCode": "AMM",
            "Type": "Station"
        },
        {
            "CityId": "AMST",
            "CityName": "Amsterdam",
            "CountryName": "Netherlands",
            "IataCode": "AMS",
            "Name": "Amsterdam",
            "PlaceId": 40595,
            "SkyscannerCode": "AMS",
            "Type": "Station"
        },
        {
            "CityId": "ASMA",
            "CityName": "Asmara",
            "CountryName": "Eritrea",
            "IataCode": "ASM",
            "Name": "Asmara",
            "PlaceId": 40877,
            "SkyscannerCode": "ASM",
            "Type": "Station"
        },
        {
            "CityId": "ASWA",
            "CityName": "Aswan Daraw",
            "CountryName": "Egypt",
            "IataCode": "ASW",
            "Name": "Aswan Daraw",
            "PlaceId": 40887,
            "SkyscannerCode": "ASW",
            "Type": "Station"
        },
        {
            "CityId": "ATHE",
            "CityName": "Athens",
            "CountryName": "Greece",
            "IataCode": "ATH",
            "Name": "Athens International",
            "PlaceId": 40920,
            "SkyscannerCode": "ATH",
            "Type": "Station"
        },
        {
            "CityId": "BARC",
            "CityName": "Barcelona",
            "CountryName": "Spain",
            "IataCode": "BCN",
            "Name": "Barcelona",
            "PlaceId": 42414,
            "SkyscannerCode": "BCN",
            "Type": "Station"
        },
        {
            "CityId": "IBOM",
            "CityName": "Mumbai",
            "CountryName": "India",
            "IataCode": "BOM",
            "Name": "Mumbai",
            "PlaceId": 42989,
            "SkyscannerCode": "BOM",
            "Type": "Station"
        },
        {
            "CityId": "PARI",
            "CityName": "Paris",
            "CountryName": "France",
            "IataCode": "CDG",
            "Name": "Paris Charles de Gaulle",
            "PlaceId": 44759,
            "SkyscannerCode": "CDG",
            "Type": "Station"
        },
        {
            "CityId": "CGKI",
            "CityName": "Jakarta",
            "CountryName": "Indonesia",
            "IataCode": "CGK",
            "Name": "Soekarno-Hatta",
            "PlaceId": 44907,
            "SkyscannerCode": "CGK",
            "Type": "Station"
        },
        {
            "CityId": "CASA",
            "CityName": "Casablanca",
            "CountryName": "Morocco",
            "IataCode": "CMN",
            "Name": "Casablanca Mohamed V.",
            "PlaceId": 45198,
            "SkyscannerCode": "CMN",
            "Type": "Station"
        },
        {
            "CityId": "EBBA",
            "CityName": "Entebbe",
            "CountryName": "Uganda",
            "IataCode": "EBB",
            "Name": "Entebbe",
            "PlaceId": 49266,
            "SkyscannerCode": "EBB",
            "Type": "Station"
        },
        {
            "CityId": "ISTA",
            "CityName": "Istanbul",
            "CountryName": "Turkey",
            "IataCode": "IST",
            "Name": "Istanbul Ataturk",
            "PlaceId": 59316,
            "SkyscannerCode": "IST",
            "Type": "Station"
        },
        {
            "CityId": "KRTA",
            "CityName": "Khartoum",
            "CountryName": "Sudan",
            "IataCode": "KRT",
            "Name": "Khartoum",
            "PlaceId": 63876,
            "SkyscannerCode": "KRT",
            "Type": "Station"
        },
        {
            "CityId": "LARN",
            "CityName": "Larnaca",
            "CountryName": "Cyprus",
            "IataCode": "LCA",
            "Name": "Larnaca",
            "PlaceId": 65441,
            "SkyscannerCode": "LCA",
            "Type": "Station"
        },
        {
            "CityId": "LVIA",
            "CityName": "Livingstone",
            "CountryName": "Zambia",
            "IataCode": "LVI",
            "Name": "Livingstone",
            "PlaceId": 66361,
            "SkyscannerCode": "LVI",
            "Type": "Station"
        },
        {
            "CityId": "MILA",
            "CityName": "Milan",
            "CountryName": "Italy",
            "IataCode": "MXP",
            "Name": "Milan Malpensa",
            "PlaceId": 68768,
            "SkyscannerCode": "MXP",
            "Type": "Station"
        },
        {
            "CityId": "NBOA",
            "CityName": "Nairobi",
            "CountryName": "Kenya",
            "IataCode": "NBO",
            "Name": "Nairobi Jomo Kenyatta",
            "PlaceId": 70015,
            "SkyscannerCode": "NBO",
            "Type": "Station"
        },
        {
            "CityId": "RUHA",
            "CityName": "Riyadh",
            "CountryName": "Saudi Arabia",
            "IataCode": "RUH",
            "Name": "Riyadh",
            "PlaceId": 80136,
            "SkyscannerCode": "RUH",
            "Type": "Station"
        },
        {
            "CityId": "BERL",
            "CityName": "Berlin",
            "CountryName": "Germany",
            "IataCode": "SXF",
            "Name": "Berlin Schoenefeld",
            "PlaceId": 82582,
            "SkyscannerCode": "SXF",
            "Type": "Station"
        },
        {
            "CityId": "TELA",
            "CityName": "Tel Aviv",
            "CountryName": "Israel",
            "IataCode": "TLV",
            "Name": "Ben Gurion Intl",
            "PlaceId": 84326,
            "SkyscannerCode": "TLV",
            "Type": "Station"
        },
        {
            "CityId": "VIEN",
            "CityName": "Vienna",
            "CountryName": "Austria",
            "IataCode": "VIE",
            "Name": "Vienna",
            "PlaceId": 88773,
            "SkyscannerCode": "VIE",
            "Type": "Station"
        },
        {
            "CityId": "ZAGR",
            "CityName": "Zagreb",
            "CountryName": "Croatia",
            "IataCode": "ZAG",
            "Name": "Zagreb",
            "PlaceId": 97607,
            "SkyscannerCode": "ZAG",
            "Type": "Station"
        }
    ],
    "Quotes": [
        {
            "Direct": false,
            "MinPrice": 267.0,
            "OutboundLeg": {
                "CarrierIds": [
                    1427
                ],
                "DepartureDate": "2017-04-29T00:00:00",
                "DestinationId": 70015,
                "OriginId": 40887
            },
            "QuoteDateTime": "2017-04-15T20:15:31",
            "QuoteId": 1
        },
        {
            "Direct": false,
            "MinPrice": 192.0,
            "OutboundLeg": {
                "CarrierIds": [
                    1427
                ],
                "DepartureDate": "2017-06-18T00:00:00",
                "DestinationId": 59316,
                "OriginId": 40887
            },
            "QuoteDateTime": "2017-03-28T14:40:33",
            "QuoteId": 2
        },
        {
            "Direct": false,
            "MinPrice": 160.0,
            "OutboundLeg": {
                "CarrierIds": [
                    1427
                ],
                "DepartureDate": "2017-07-21T00:00:00",
                "DestinationId": 80136,
                "OriginId": 40887
            },
            "QuoteDateTime": "2017-03-21T05:18:04",
            "QuoteId": 3
        },
        {
            "Direct": false,
            "MinPrice": 178.0,
            "OutboundLeg": {
                "CarrierIds": [
                    1427
                ],
                "DepartureDate": "2017-08-08T00:00:00",
                "DestinationId": 40589,
                "OriginId": 40887
            },
            "QuoteDateTime": "2017-03-26T13:36:46",
            "QuoteId": 4
        },
        {
            "Direct": false,
            "MinPrice": 297.0,
            "OutboundLeg": {
                "CarrierIds": [
                    1427
                ],
                "DepartureDate": "2017-06-07T00:00:00",
                "DestinationId": 40877,
                "OriginId": 40887
            },
            "QuoteDateTime": "2017-03-30T11:43:03",
            "QuoteId": 5
        },
        {
            "Direct": false,
            "MinPrice": 194.0,
            "OutboundLeg": {
                "CarrierIds": [
                    1427
                ],
                "DepartureDate": "2017-05-01T00:00:00",
                "DestinationId": 65441,
                "OriginId": 40887
            },
            "QuoteDateTime": "2017-03-24T08:13:15",
            "QuoteId": 6
        },
        {
            "Direct": false,
            "MinPrice": 227.0,
            "OutboundLeg": {
                "CarrierIds": [
                    1427
                ],
                "DepartureDate": "2017-06-11T00:00:00",
                "DestinationId": 42989,
                "OriginId": 40887
            },
            "QuoteDateTime": "2017-03-25T10:35:43",
            "QuoteId": 7
        },
        {
            "Direct": false,
            "MinPrice": 213.0,
            "OutboundLeg": {
                "CarrierIds": [
                    1427
                ],
                "DepartureDate": "2017-05-26T00:00:00",
                "DestinationId": 88773,
                "OriginId": 40887
            },
            "QuoteDateTime": "2017-03-28T14:20:04",
            "QuoteId": 8
        },
        {
            "Direct": false,
            "MinPrice": 261.0,
            "OutboundLeg": {
                "CarrierIds": [
                    1427
                ],
                "DepartureDate": "2017-05-09T00:00:00",
                "DestinationId": 42414,
                "OriginId": 40887
            },
            "QuoteDateTime": "2017-04-09T21:39:37",
            "QuoteId": 9
        },
        {
            "Direct": false,
            "MinPrice": 262.0,
            "OutboundLeg": {
                "CarrierIds": [
                    1427
                ],
                "DepartureDate": "2017-05-20T00:00:00",
                "DestinationId": 63876,
                "OriginId": 40887
            },
            "QuoteDateTime": "2017-03-27T18:32:24",
            "QuoteId": 10
        },
        {
            "Direct": false,
            "MinPrice": 225.0,
            "OutboundLeg": {
                "CarrierIds": [
                    1427
                ],
                "DepartureDate": "2017-05-09T00:00:00",
                "DestinationId": 45198,
                "OriginId": 40887
            },
            "QuoteDateTime": "2017-04-14T18:57:00",
            "QuoteId": 11
        },
        {
            "Direct": false,
            "MinPrice": 256.0,
            "OutboundLeg": {
                "CarrierIds": [
                    1427
                ],
                "DepartureDate": "2018-01-05T00:00:00",
                "DestinationId": 49266,
                "OriginId": 40887
            },
            "QuoteDateTime": "2017-03-24T15:04:45",
            "QuoteId": 12
        },
        {
            "Direct": false,
            "MinPrice": 240.0,
            "OutboundLeg": {
                "CarrierIds": [
                    1427
                ],
                "DepartureDate": "2017-06-07T00:00:00",
                "DestinationId": 68768,
                "OriginId": 40887
            },
            "QuoteDateTime": "2017-04-18T19:09:22",
            "QuoteId": 13
        },
        {
            "Direct": false,
            "MinPrice": 146.0,
            "OutboundLeg": {
                "CarrierIds": [
                    819
                ],
                "DepartureDate": "2017-06-24T00:00:00",
                "DestinationId": 40920,
                "OriginId": 40887
            },
            "QuoteDateTime": "2017-03-16T04:01:16",
            "QuoteId": 14
        },
        {
            "Direct": false,
            "MinPrice": 255.0,
            "OutboundLeg": {
                "CarrierIds": [
                    1427
                ],
                "DepartureDate": "2017-09-15T00:00:00",
                "DestinationId": 40595,
                "OriginId": 40887
            },
            "QuoteDateTime": "2017-03-28T16:22:18",
            "QuoteId": 15
        },
        {
            "Direct": false,
            "MinPrice": 268.0,
            "OutboundLeg": {
                "CarrierIds": [
                    1427
                ],
                "DepartureDate": "2017-05-03T00:00:00",
                "DestinationId": 44759,
                "OriginId": 40887
            },
            "QuoteDateTime": "2017-04-14T15:03:16",
            "QuoteId": 16
        },
        {
            "Direct": false,
            "MinPrice": 217.0,
            "OutboundLeg": {
                "CarrierIds": [
                    1427
                ],
                "DepartureDate": "2017-05-25T00:00:00",
                "DestinationId": 82582,
                "OriginId": 40887
            },
            "QuoteDateTime": "2017-03-26T10:20:44",
            "QuoteId": 17
        },
        {
            "Direct": false,
            "MinPrice": 642.0,
            "OutboundLeg": {
                "CarrierIds": [],
                "DepartureDate": "2018-02-20T00:00:00",
                "DestinationId": 84326,
                "OriginId": 40887
            },
            "QuoteDateTime": "2017-03-20T20:10:50",
            "QuoteId": 18
        },
        {
            "Direct": false,
            "MinPrice": 454.0,
            "OutboundLeg": {
                "CarrierIds": [],
                "DepartureDate": "2017-05-10T00:00:00",
                "DestinationId": 44907,
                "OriginId": 40887
            },
            "QuoteDateTime": "2017-04-06T21:19:30",
            "QuoteId": 19
        },
        {
            "Direct": false,
            "MinPrice": 966.0,
            "OutboundLeg": {
                "CarrierIds": [],
                "DepartureDate": "2017-11-10T00:00:00",
                "DestinationId": 66361,
                "OriginId": 40887
            },
            "QuoteDateTime": "2017-04-09T02:30:02",
            "QuoteId": 20
        },
        {
            "Direct": false,
            "MinPrice": 418.0,
            "OutboundLeg": {
                "CarrierIds": [],
                "DepartureDate": "2017-07-12T00:00:00",
                "DestinationId": 97607,
                "OriginId": 40887
            },
            "QuoteDateTime": "2017-04-06T05:43:59",
            "QuoteId": 21
        }
    ],
    "Routes": [
        {
            "DestinationId": 1752,
            "OriginId": 40887
        },
        {
            "DestinationId": 934,
            "OriginId": 40887
        },
        {
            "DestinationId": 1317,
            "OriginId": 40887,
            "Price": 267.0,
            "QuoteDateTime": "2017-04-15T20:15:31",
            "QuoteIds": [
                1
            ]
        },
        {
            "DestinationId": 1762,
            "OriginId": 40887,
            "Price": 192.0,
            "QuoteDateTime": "2017-03-28T14:40:33",
            "QuoteIds": [
                2
            ]
        },
        {
            "DestinationId": 1697,
            "OriginId": 40887,
            "Price": 160.0,
            "QuoteDateTime": "2017-03-21T05:18:04",
            "QuoteIds": [
                3
            ]
        },
        {
            "DestinationId": 888,
            "OriginId": 40887
        },
        {
            "DestinationId": 1279,
            "OriginId": 40887,
            "Price": 178.0,
            "QuoteDateTime": "2017-03-26T13:36:46",
            "QuoteIds": [
                4
            ]
        },
        {
            "DestinationId": 1601,
            "OriginId": 40887
        },
        {
            "DestinationId": 1031,
            "OriginId": 40887
        },
        {
            "DestinationId": 1044,
            "OriginId": 40887
        },
        {
            "DestinationId": 1042,
            "OriginId": 40887,
            "Price": 297.0,
            "QuoteDateTime": "2017-03-30T11:43:03",
            "QuoteIds": [
                5
            ]
        },
        {
            "DestinationId": 1128,
            "OriginId": 40887
        },
        {
            "DestinationId": 1002,
            "OriginId": 40887
        },
        {
            "DestinationId": 1335,
            "OriginId": 40887
        },
        {
            "DestinationId": 1517,
            "OriginId": 40887
        },
        {
            "DestinationId": 929,
            "OriginId": 40887
        },
        {
            "DestinationId": 953,
            "OriginId": 40887,
            "Price": 194.0,
            "QuoteDateTime": "2017-03-24T08:13:15",
            "QuoteIds": [
                6
            ]
        },
        {
            "DestinationId": 837,
            "OriginId": 40887
        },
        {
            "DestinationId": 1362,
            "OriginId": 40887
        },
        {
            "DestinationId": 1233,
            "OriginId": 40887
        },
        {
            "DestinationId": 1811,
            "OriginId": 40887
        },
        {
            "DestinationId": 942,
            "OriginId": 40887
        },
        {
            "DestinationId": 1230,
            "OriginId": 40887,
            "Price": 227.0,
            "QuoteDateTime": "2017-03-25T10:35:43",
            "QuoteIds": [
                7
            ]
        },
        {
            "DestinationId": 1758,
            "OriginId": 40887
        },
        {
            "DestinationId": 852,
            "OriginId": 40887,
            "Price": 213.0,
            "QuoteDateTime": "2017-03-28T14:20:04",
            "QuoteIds": [
                8
            ]
        },
        {
            "DestinationId": 1043,
            "OriginId": 40887,
            "Price": 261.0,
            "QuoteDateTime": "2017-04-09T21:39:37",
            "QuoteIds": [
                9
            ]
        },
        {
            "DestinationId": 987,
            "OriginId": 40887
        },
        {
            "DestinationId": 1770,
            "OriginId": 40887
        },
        {
            "DestinationId": 1463,
            "OriginId": 40887
        },
        {
            "DestinationId": 1700,
            "OriginId": 40887,
            "Price": 262.0,
            "QuoteDateTime": "2017-03-27T18:32:24",
            "QuoteIds": [
                10
            ]
        },
        {
            "DestinationId": 1748,
            "OriginId": 40887
        },
        {
            "DestinationId": 2033,
            "OriginId": 40887
        },
        {
            "DestinationId": 1409,
            "OriginId": 40887,
            "Price": 225.0,
            "QuoteDateTime": "2017-04-14T18:57:00",
            "QuoteIds": [
                11
            ]
        },
        {
            "DestinationId": 1799,
            "OriginId": 40887,
            "Price": 256.0,
            "QuoteDateTime": "2017-03-24T15:04:45",
            "QuoteIds": [
                12
            ]
        },
        {
            "DestinationId": 1236,
            "OriginId": 40887,
            "Price": 240.0,
            "QuoteDateTime": "2017-04-18T19:09:22",
            "QuoteIds": [
                13
            ]
        },
        {
            "DestinationId": 1189,
            "OriginId": 40887
        },
        {
            "DestinationId": 1138,
            "OriginId": 40887,
            "Price": 146.0,
            "QuoteDateTime": "2017-03-16T04:01:16",
            "QuoteIds": [
                14
            ]
        },
        {
            "DestinationId": 1468,
            "OriginId": 40887,
            "Price": 255.0,
            "QuoteDateTime": "2017-03-28T16:22:18",
            "QuoteIds": [
                15
            ]
        },
        {
            "DestinationId": 885,
            "OriginId": 40887
        },
        {
            "DestinationId": 936,
            "OriginId": 40887
        },
        {
            "DestinationId": 1090,
            "OriginId": 40887,
            "Price": 268.0,
            "QuoteDateTime": "2017-04-14T15:03:16",
            "QuoteIds": [
                16
            ]
        },
        {
            "DestinationId": 1803,
            "OriginId": 40887
        },
        {
            "DestinationId": 981,
            "OriginId": 40887,
            "Price": 217.0,
            "QuoteDateTime": "2017-03-26T10:20:44",
            "QuoteIds": [
                17
            ]
        },
        {
            "DestinationId": 1715,
            "OriginId": 40887
        },
        {
            "DestinationId": 1433,
            "OriginId": 40887
        },
        {
            "DestinationId": 937,
            "OriginId": 40887
        },
        {
            "DestinationId": 1228,
            "OriginId": 40887,
            "Price": 642.0,
            "QuoteDateTime": "2017-03-20T20:10:50",
            "QuoteIds": [
                18
            ]
        },
        {
            "DestinationId": 1220,
            "OriginId": 40887,
            "Price": 454.0,
            "QuoteDateTime": "2017-04-06T21:19:30",
            "QuoteIds": [
                19
            ]
        },
        {
            "DestinationId": 2045,
            "OriginId": 40887,
            "Price": 966.0,
            "QuoteDateTime": "2017-04-09T02:30:02",
            "QuoteIds": [
                20
            ]
        },
        {
            "DestinationId": 1186,
            "OriginId": 40887,
            "Price": 418.0,
            "QuoteDateTime": "2017-04-06T05:43:59",
            "QuoteIds": [
                21
            ]
        }
    ]
}